bazis_test_utils/__init__.py
bazis_test_utils/_version.py
bazis_test_utils/factories_abstract.py
bazis_test_utils/models_abstract.py
bazis_test_utils/utils.py
bazis_test_utils/locale/messages.pot
bazis_test_utils/locale/en/LC_MESSAGES/django.mo
bazis_test_utils/locale/en/LC_MESSAGES/django.po
bazis_test_utils/locale/ru/LC_MESSAGES/django.mo
bazis_test_utils/locale/ru/LC_MESSAGES/django.po
bazis_test_utils-2.2.1.dist-info/licenses/LICENSE
bazis_test_utils-2.2.1.dist-info/licenses/NOTICE
bazis_test_utils-2.2.1.dist-info/METADATA
bazis_test_utils-2.2.1.dist-info/WHEEL
bazis_test_utils-2.2.1.dist-info/top_level.txt
bazis_test_utils-2.2.1.dist-info/RECORD
