Metadata-Version: 2.4
Name: bazis-test-utils
Version: 2.2.1
Summary: A utility package for testing in the Bazis ecosystem — a framework based on Django + FastAPI + Pydantic.
Author-email: Ilya Kharyn <ilya.tt07@gmail.com>
Maintainer-email: Ilya Kharyn <ilya.tt07@gmail.com>
License-Expression: Apache-2.0
Project-URL: Home, https://github.com/ecofuture-tech/bazis-test-utils
Keywords: bazis,django,fastapi,pydantic,framework,jsonapi,test-utilities
Classifier: Intended Audience :: Developers
Classifier: Topic :: Software Development :: Libraries :: Python Modules
Classifier: Operating System :: OS Independent
Classifier: Programming Language :: Python :: 3
Classifier: Programming Language :: Python :: 3.12
Classifier: Programming Language :: Python :: 3.13
Classifier: Programming Language :: Python :: 3.14
Classifier: Framework :: Django
Classifier: Framework :: FastAPI
Requires-Python: >=3.12
License-File: LICENSE
License-File: NOTICE
Requires-Dist: django
Requires-Dist: fastapi
Requires-Dist: factory_boy
Requires-Dist: httpx<=0.27.0
Requires-Dist: pytest
Requires-Dist: pytest-django
Requires-Dist: pytest-mock
Requires-Dist: requests
Requires-Dist: requests-toolbelt
Requires-Dist: requests-mock
Requires-Dist: uvicorn[standard]
Provides-Extra: dev
Requires-Dist: ruff; extra == "dev"
Dynamic: license-file
